we_factor_quad/__init__.py
we_factor_quad/client_local.py
we_factor_quad/constants.py
we_factor_quad/data_api.py
we_factor_quad/factor_macro.py
we_factor_quad/factor_quad.py
we_factor_quad/factor_quad_settings.py
we_factor_quad/param.py
we_factor_quad/utils.py
we_factor_quad/workshop.py
we_factor_quad/characteristic/__init__.py
we_factor_quad/characteristic/characteristic_exposure.py
we_factor_quad/commodity_quad/__init__.py
we_factor_quad/commodity_quad/factor_quad_commodity.py
we_factor_quad/commodity_quad/factor_portfolio/__init__.py
we_factor_quad/commodity_quad/risk_control/__init__.py
we_factor_quad/equity_quad/__init__.py
we_factor_quad/equity_quad/daily_data_update_preprocessing.py
we_factor_quad/equity_quad/factor_quad_equity.py
we_factor_quad/equity_quad/fix_missing_psi.py
we_factor_quad/equity_quad/solve_colinear.py
we_factor_quad/equity_quad/factor_portfolio/__init__.py
we_factor_quad/equity_quad/factor_portfolio/check_industrial_factors.py
we_factor_quad/equity_quad/factor_portfolio/compare_independency.py
we_factor_quad/equity_quad/factor_portfolio/corr_plot_helper.py
we_factor_quad/equity_quad/factor_portfolio/daily_update_everything_with_country.py
we_factor_quad/equity_quad/factor_portfolio/daily_update_factor_return.py
we_factor_quad/equity_quad/factor_portfolio/full_factor_mimicking_portfolio.py
we_factor_quad/equity_quad/factor_portfolio/universe_helper.py
we_factor_quad/equity_quad/factor_portfolio/upload_daily_return.py
we_factor_quad/equity_quad/factor_portfolio/upload_factor_return.py
we_factor_quad/equity_quad/factor_portfolio/upload_fmp_weights.py
we_factor_quad/equity_quad/factor_portfolio/xintouyan.py
we_factor_quad/equity_quad/risk_control/__init__.py
we_factor_quad/equity_quad/risk_control/index_risk_control.py
we_factor_quad/equity_quad/risk_control/portfolio_risk_control.py
we_factor_quad/equity_quad/risk_control/stock_risk_control.py
we_factor_quad/equity_quad/risk_control/stock_risk_control_daily.py
we_factor_quad-0.6.0.dist-info/METADATA
we_factor_quad-0.6.0.dist-info/WHEEL
we_factor_quad-0.6.0.dist-info/top_level.txt
we_factor_quad-0.6.0.dist-info/zip-safe
we_factor_quad-0.6.0.dist-info/RECORD
